<?xml version="1.0" encoding="UTF-8"?>
<objects serializationModel="Studio.02.02.00">
	<object class="AudioFile" id="{2293be5b-7a56-4a5a-8ca6-4d1a9e970cbe}">
		<property name="assetPath">
			<value>Player/TakenDamage/SFX_PLAYER_DAMAGE_ZAPS/SFX_PLAYER_DAMAGE_ZAPS_03.wav</value>
		</property>
		<property name="frequencyInKHz">
			<value>48</value>
		</property>
		<property name="channelCount">
			<value>1</value>
		</property>
		<property name="length">
			<value>0.64439583333333328</value>
		</property>
		<relationship name="masterAssetFolder">
			<destination>{ac5f5264-6d3e-4c54-93a0-f535a51777e4}</destination>
		</relationship>
	</object>
</objects>
