<?xml version="1.0" encoding="UTF-8"?>
<objects serializationModel="Studio.02.02.00">
	<object class="AudioFile" id="{ae07083b-2a56-428a-a3e8-7ff57284e28e}">
		<property name="assetPath">
			<value>Player/Movement/Footsteps/SFX_PLAYER_FS_R/SFX_PLAYER_FS_R_01.wav</value>
		</property>
		<property name="frequencyInKHz">
			<value>48</value>
		</property>
		<property name="channelCount">
			<value>1</value>
		</property>
		<property name="length">
			<value>0.50049999999999994</value>
		</property>
		<relationship name="masterAssetFolder">
			<destination>{ac5f5264-6d3e-4c54-93a0-f535a51777e4}</destination>
		</relationship>
	</object>
</objects>
