<?xml version="1.0" encoding="UTF-8"?>
<objects serializationModel="Studio.02.02.00">
	<object class="AudioFile" id="{decdf9d1-475d-478a-8de5-69cd95e393aa}">
		<property name="assetPath">
			<value>SFX/Truck/SFX_KICK_TRUCK/SFX_KICK_TRUCK_METAL_IMPACT_TONAL/SFX_KICK_TRUCK_METAL_IMPACT_TONAL_04.wav</value>
		</property>
		<property name="frequencyInKHz">
			<value>48</value>
		</property>
		<property name="channelCount">
			<value>1</value>
		</property>
		<property name="length">
			<value>0.7069375</value>
		</property>
		<relationship name="masterAssetFolder">
			<destination>{ac5f5264-6d3e-4c54-93a0-f535a51777e4}</destination>
		</relationship>
	</object>
</objects>
